libschema/__init__.py
libschema/analysis.py
libschema/bmi.py
libschema/classes.py
libschema/model.py
libschema-0.2.1.dist-info/licenses/LICENSE
libschema-0.2.1.dist-info/METADATA
libschema-0.2.1.dist-info/WHEEL
libschema-0.2.1.dist-info/top_level.txt
libschema-0.2.1.dist-info/RECORD
