Metadata-Version: 2.4
Name: libschema
Version: 0.2.1
Summary: Generic Python implementation of the SCHEMA modeling framework with built-in BMI/ngen support.  SCHEMA = Seasonal Conditions Historical Expectation with Modeled Anomaly.
Home-page: https://www.rivertempest.org/libschema/readme.html
Author: Daniel Philippus
Author-email: daniel@dphilippus.com
Project-URL: Bug Tracker, https://github.com/mines-ciroh/libSCHEMA/issues
Project-URL: Source Code, https://github.com/mines-ciroh/libSCHEMA
Classifier: Programming Language :: Python :: 3
Classifier: License :: OSI Approved :: GNU General Public License v3 (GPLv3)
Requires-Python: >=3.0
License-File: LICENSE
Requires-Dist: pandas
Requires-Dist: numpy
Requires-Dist: pyyaml
Requires-Dist: bmipy
Dynamic: license-file
